setup.cfg
setup.py
crocus/__init__.py
crocus/application.py
crocus/errors.py
crocus/helpers.py
crocus/request.py
crocus/response.py
crocus/server.py
crocus.egg-info/PKG-INFO
crocus.egg-info/SOURCES.txt
crocus.egg-info/dependency_links.txt
crocus.egg-info/not-zip-safe
crocus.egg-info/requires.txt
crocus.egg-info/top_level.txt