Metadata-Version: 1.1
Name: crocus
Version: 0.3.0
Summary: Python async http framework with asyncio + aiohttp (requires 3.5+)
Home-page: https://github.com/goldark/crocus
Author: Leonardo Rossetti
Author-email: leonardo@goldark.com.br
License: MIT
Keywords: async,http,server,web framework,async http,asyncio
Platform: UNKNOWN
Classifier: Topic :: Internet :: WWW/HTTP :: HTTP Servers
Classifier: Topic :: Software Development :: Libraries :: Application Frameworks
